bitio.py
BitIO2-1.1.0.dist-info/LICENSE
BitIO2-1.1.0.dist-info/METADATA
BitIO2-1.1.0.dist-info/WHEEL
BitIO2-1.1.0.dist-info/top_level.txt
BitIO2-1.1.0.dist-info/RECORD
