Metadata-Version: 2.1
Name: BitIO2
Version: 1.1.0
Summary: A library for manipulating files via bits
Home-page: https://github.com/gaming32/BitIO
Author: Gaming32
Author-email: gaming32i64@gmail.com
License: License :: OSI Approved :: MIT License
Platform: UNKNOWN
Requires-Dist: bitarray
